README.md
setup.py
cosdem/__init__.py
cosdem/cosdem.py
cosdem.egg-info/PKG-INFO
cosdem.egg-info/SOURCES.txt
cosdem.egg-info/dependency_links.txt
cosdem.egg-info/requires.txt
cosdem.egg-info/top_level.txt
cosdem.egg-info/zip-safe