Metadata-Version: 2.1
Name: cosdem
Version: 0.0.1
Summary: Comparing Statistical Differences of Measurements
Home-page: http://github.com/yigitsener/cosdem_project
Author: Yiğit Şener
Author-email: dataevreni@gmail.com
License: MIT
Keywords: Statistical Difference Tests,t test,regression,correlation,mann wihtney u test,Homogeneity Tests,Normality Test,Descriptive Statistics,bland altman plot,violin plot
Platform: UNKNOWN
Classifier: Programming Language :: Python
Classifier: Programming Language :: Python :: 3.6
Classifier: Programming Language :: Python :: 3.7
Classifier: Programming Language :: Python :: 3.8
Classifier: Intended Audience :: Science/Research
Classifier: License :: OSI Approved :: MIT License
Classifier: Operating System :: OS Independent
Classifier: Topic :: Scientific/Engineering :: Information Analysis
Classifier: Topic :: Scientific/Engineering :: Visualization
Requires-Python: >=3.6.*
